jdit/__init__.py
jdit/dataset.py
jdit/model.py
jdit/optimizer.py
jdit/perspective.py
jdit/assessment/__init__.py
jdit/assessment/fid.py
jdit/assessment/inception.py
jdit/parallel/__init__.py
jdit/parallel/parallel_trainer.py
jdit/trainer/__init__.py
jdit/trainer/abandon_classification.py
jdit/trainer/super.py
jdit/trainer/gan/__init__.py
jdit/trainer/gan/generate.py
jdit/trainer/gan/pix2pix.py
jdit/trainer/gan/sup_gan.py
jdit/trainer/instances/__init__.py
jdit/trainer/instances/cifarPix2pixGan.py
jdit/trainer/instances/fashionAutoencoder.py
jdit/trainer/instances/fashionClassParallelTrainer.py
jdit/trainer/instances/fashionClassification.py
jdit/trainer/instances/fashionGenerateGan.py
jdit/trainer/single/__init__.py
jdit/trainer/single/autoencoder.py
jdit/trainer/single/classification.py
jdit/trainer/single/sup_single.py
jdit-0.1.5.dist-info/LICENSE
jdit-0.1.5.dist-info/METADATA
jdit-0.1.5.dist-info/WHEEL
jdit-0.1.5.dist-info/top_level.txt
jdit-0.1.5.dist-info/RECORD
