Metadata-Version: 2.1
Name: jdit
Version: 0.1.5
Summary: Make it easy to do research on pytorch
Home-page: https://github.com/dingguanglei/jdit
Author: Guanglei Ding
Author-email: dingguanglei.bupt@qq.com
Maintainer: Guanglei Ding
Maintainer-email: dingguanglei.bupt@qq.com
License: Apache License 2.0
Keywords: pytorch research framework
Platform: all
Classifier: Topic :: Scientific/Engineering :: Artificial Intelligence
Classifier: License :: OSI Approved :: Apache Software License
Classifier: Development Status :: 4 - Beta
Classifier: Operating System :: OS Independent
Classifier: Intended Audience :: Developers
Classifier: Programming Language :: Python :: 3 :: Only
Classifier: Programming Language :: Python :: Implementation
Classifier: Programming Language :: Python :: 3.6
Classifier: Programming Language :: Python :: 3.7
Classifier: Programming Language :: Python :: Implementation :: CPython
Classifier: Topic :: Scientific/Engineering :: Artificial Intelligence
Classifier: Topic :: Scientific/Engineering :: Visualization  
Requires-Dist: nvidia-ml-py3 (>=7.352.0)
Requires-Dist: imageio
